[
  {
    "title": "Non disponible",
    "rating": "Non disponible",
    "reviews": "Non disponible",
    "address": "Non disponible",
    "phone": " 41.40338",
    "website": "https://www.google.tn/intl/ar/about/products?tab=uh"
  },
  {
    "title": "The 716 Menzah 6",
    "rating": "Non disponible",
    "reviews": "Non disponible",
    "address": "\nV527+VW6، أريانة",
    "phone": "\n71 766 730",
    "website": "https://glovoapp.com/tn/fr/tunis-1-tunis-centre-menzah-manar/the-716-tis?utm_source=google&utm_medium=organic&utm_campaign=google_reserve_place_order_action"
  },
  {
    "title": "The Five",
    "rating": "Non disponible",
    "reviews": "Non disponible",
    "address": "\n6 Rue Ammar Ibn Yesser, Ariana",
    "phone": "\n28 888 479",
    "website": "https://glovoapp.com/tn/fr/tunis-1-tunis-centre-menzah-manar/the-five-tis?utm_source=google&utm_medium=organic&utm_campaign=google_reserve_place_order_action"
  },
  {
    "title": "Le Montmartre",
    "rating": "Non disponible",
    "reviews": "Non disponible",
    "address": "\n1 Bis, Rue Tahar Memmi, Ariana 2091",
    "phone": "\n92 382 384",
    "website": "https://www.facebook.com/montmartre.tn/"
  },
  {
    "title": "café 23",
    "rating": "Non disponible",
    "reviews": "Non disponible",
    "address": "\nRue Aboubakher el Khawarizmi, Ariana",
    "phone": "\n23 223 332",
    "website": "https://support.google.com/contributionpolicy/answer/7400114?ref_topic=7422769"
  },
  {
    "title": "Sacré Cœur",
    "rating": "Non disponible",
    "reviews": "Non disponible",
    "address": "\nR5W7+FW4، أريانة",
    "phone": "\n22 911 404",
    "website": "https://business.google.com/create?fp=15943939130892504377&hl=ar&authuser=0&gmbsrc=tn-ar-et-ip-z-gmb-s-z-l~mrc%7Cclaimbz%7Cu&ppsrc=GMBMI&utm_campaign=tn-ar-et-ip-z-gmb-s-z-l~mrc%7Cclaimbz%7Cu&utm_source=gmb_mrc81&utm_medium=et&getstarted&lis=0"
  },
  {
    "title": "The Hyphen",
    "rating": "Non disponible",
    "reviews": "Non disponible",
    "address": "\nRue Cheikh Zaghouani, Ariana",
    "phone": "\n27 125 777",
    "website": "https://support.google.com/contributionpolicy/answer/7400114?ref_topic=7422769"
  },
  {
    "title": "Beya Coffe shop Menzah 6",
    "rating": "Non disponible",
    "reviews": "Non disponible",
    "address": "\n7 bis cité jamil, Ariana 2091",
    "phone": "\n55 053 002",
    "website": "https://support.google.com/contributionpolicy/answer/7400114?ref_topic=7422769"
  },
  {
    "title": "Café",
    "rating": "Non disponible",
    "reviews": "Non disponible",
    "address": "\nR5X9+78X, Rue Cheikh Zaghouani, Ariana",
    "phone": "Non disponible",
    "website": "https://business.google.com/create?fp=13051748484607304029&hl=ar&authuser=0&gmbsrc=tn-ar-et-ip-z-gmb-s-z-l~mrc%7Cclaimbz%7Cu&ppsrc=GMBMI&utm_campaign=tn-ar-et-ip-z-gmb-s-z-l~mrc%7Cclaimbz%7Cu&utm_source=gmb_mrc81&utm_medium=et&getstarted&lis=0"
  },
  {
    "title": "3al Kif",
    "rating": "Non disponible",
    "reviews": "Non disponible",
    "address": "\nR5W8+9XC، أريانة",
    "phone": "\n97 614 639",
    "website": "https://business.google.com/create?fp=9869382504629988859&hl=ar&authuser=0&gmbsrc=tn-ar-et-ip-z-gmb-s-z-l~mrc%7Cclaimbz%7Cu&ppsrc=GMBMI&utm_campaign=tn-ar-et-ip-z-gmb-s-z-l~mrc%7Cclaimbz%7Cu&utm_source=gmb_mrc81&utm_medium=et&getstarted&lis=0"
  },
  {
    "title": "Upper",
    "rating": "Non disponible",
    "reviews": "Non disponible",
    "address": "\n1 Rue Ammar Ibn Yesser, Ariana",
    "phone": "\n29 574 888",
    "website": "https://business.google.com/create?fp=16165501533107022982&hl=ar&authuser=0&gmbsrc=tn-ar-et-ip-z-gmb-s-z-l~mrc%7Cclaimbz%7Cu&ppsrc=GMBMI&utm_campaign=tn-ar-et-ip-z-gmb-s-z-l~mrc%7Cclaimbz%7Cu&utm_source=gmb_mrc81&utm_medium=et&getstarted&lis=0"
  },
  {
    "title": "Café Mechméch",
    "rating": "Non disponible",
    "reviews": "Non disponible",
    "address": "\nCité Jamil, Tunis 2036",
    "phone": "Non disponible",
    "website": "https://support.google.com/contributionpolicy/answer/7400114?ref_topic=7422769"
  },
  {
    "title": "MAK Coffee Lounge",
    "rating": "Non disponible",
    "reviews": "Non disponible",
    "address": "\n18 Rue des juges, Ariana 2091",
    "phone": "\n51 233 533",
    "website": "https://www.facebook.com/MakCoffeeLounge/"
  },
  {
    "title": "كفيتيريا الفنون",
    "rating": "Non disponible",
    "reviews": "Non disponible",
    "address": "\nV535+3WX, Rue El Amir Abdelkader El Jazairi, Ariana",
    "phone": "Non disponible",
    "website": "https://business.google.com/create?fp=10957514840282982564&hl=ar&authuser=0&gmbsrc=tn-ar-et-ip-z-gmb-s-z-l~mrc%7Cclaimbz%7Cu&ppsrc=GMBMI&utm_campaign=tn-ar-et-ip-z-gmb-s-z-l~mrc%7Cclaimbz%7Cu&utm_source=gmb_mrc81&utm_medium=et&getstarted&lis=0"
  },
  {
    "title": "Florian Coffeeshop",
    "rating": "Non disponible",
    "reviews": "Non disponible",
    "address": "\n17 Rue Ammar Ibn Yesser, Ariana",
    "phone": "Non disponible",
    "website": "https://business.google.com/create?fp=378697509479928021&hl=ar&authuser=0&gmbsrc=tn-ar-et-ip-z-gmb-s-z-l~mrc%7Cclaimbz%7Cu&ppsrc=GMBMI&utm_campaign=tn-ar-et-ip-z-gmb-s-z-l~mrc%7Cclaimbz%7Cu&utm_source=gmb_mrc81&utm_medium=et&getstarted&lis=0"
  },
  {
    "title": "Rustica Menzah 6",
    "rating": "Non disponible",
    "reviews": "Non disponible",
    "address": "\nأريانة",
    "phone": "\n22 660 103",
    "website": "https://www.facebook.com/RusticaMenzah6/"
  },
  {
    "title": "Piccolo",
    "rating": "Non disponible",
    "reviews": "Non disponible",
    "address": "\nR5W8+P45، أريانة",
    "phone": "\n71 751 999",
    "website": "https://business.google.com/create?fp=4921364425819732224&hl=ar&authuser=0&gmbsrc=tn-ar-et-ip-z-gmb-s-z-l~mrc%7Cclaimbz%7Cu&ppsrc=GMBMI&utm_campaign=tn-ar-et-ip-z-gmb-s-z-l~mrc%7Cclaimbz%7Cu&utm_source=gmb_mrc81&utm_medium=et&getstarted&lis=0"
  },
  {
    "title": "salon de thé l'image",
    "rating": "Non disponible",
    "reviews": "Non disponible",
    "address": "\nR5W8+MJM, Unnamed Road, Ariana",
    "phone": "\n70 816 422",
    "website": "https://www.facebook.com/Limage-salon-de-th%C3%A9-108067368579603/"
  },
  {
    "title": "WoodStock Cafè",
    "rating": "Non disponible",
    "reviews": "Non disponible",
    "address": "\nV52C+87J, Av. Othman Ibn Affane, Ariana",
    "phone": "\n58 176 108",
    "website": "https://www.facebook.com/WoodStock-caf%C3%A9-103711510993290/"
  },
  {
    "title": "Dar Fatma",
    "rating": "Non disponible",
    "reviews": "Non disponible",
    "address": "\nR5V9+X22, Rue Ahmed Tlili, Ariana",
    "phone": "\n23 463 000",
    "website": "https://business.google.com/create?fp=15754478608435672304&hl=ar&authuser=0&gmbsrc=tn-ar-et-ip-z-gmb-s-z-l~mrc%7Cclaimbz%7Cu&ppsrc=GMBMI&utm_campaign=tn-ar-et-ip-z-gmb-s-z-l~mrc%7Cclaimbz%7Cu&utm_source=gmb_mrc81&utm_medium=et&getstarted&lis=0"
  },
  {
    "title": "Café Bondin",
    "rating": "Non disponible",
    "reviews": "Non disponible",
    "address": "\nR5W8+M8M، أريانة",
    "phone": "\n71 232 240",
    "website": "https://business.google.com/create?fp=8765980756205358699&hl=ar&authuser=0&gmbsrc=tn-ar-et-ip-z-gmb-s-z-l~mrc%7Cclaimbz%7Cu&ppsrc=GMBMI&utm_campaign=tn-ar-et-ip-z-gmb-s-z-l~mrc%7Cclaimbz%7Cu&utm_source=gmb_mrc81&utm_medium=et&getstarted&lis=0"
  },
  {
    "title": "5'12 Coffee Shop",
    "rating": "Non disponible",
    "reviews": "Non disponible",
    "address": "\n17 Rue Ammar Ibn Yesser, Ariana 2091",
    "phone": "Non disponible",
    "website": "https://business.google.com/create?fp=12880956767684031209&hl=ar&authuser=0&gmbsrc=tn-ar-et-ip-z-gmb-s-z-l~mrc%7Cclaimbz%7Cu&ppsrc=GMBMI&utm_campaign=tn-ar-et-ip-z-gmb-s-z-l~mrc%7Cclaimbz%7Cu&utm_source=gmb_mrc81&utm_medium=et&getstarted&lis=0"
  },
  {
    "title": "TOAST",
    "rating": "Non disponible",
    "reviews": "Non disponible",
    "address": "\n19 Rue Mustapha Abdessalem, Ariana",
    "phone": "\n97 843 890",
    "website": "https://support.google.com/contributionpolicy/answer/7400114?ref_topic=7422769"
  },
  {
    "title": "cafe des arts cite jamil",
    "rating": "Non disponible",
    "reviews": "Non disponible",
    "address": "\nR5W8+JRF، أريانة",
    "phone": "Non disponible",
    "website": "https://business.google.com/create?fp=3871160977599915566&hl=ar&authuser=0&gmbsrc=tn-ar-et-ip-z-gmb-s-z-l~mrc%7Cclaimbz%7Cu&ppsrc=GMBMI&utm_campaign=tn-ar-et-ip-z-gmb-s-z-l~mrc%7Cclaimbz%7Cu&utm_source=gmb_mrc81&utm_medium=et&getstarted&lis=0"
  },
  {
    "title": "La Seine",
    "rating": "Non disponible",
    "reviews": "Non disponible",
    "address": "\n2 Rue Tahar Memmi, Ariana 2091",
    "phone": "\n52 516 415",
    "website": "https://www.facebook.com/laseine.tn/"
  },
  {
    "title": "Le 49 Bis",
    "rating": "Non disponible",
    "reviews": "Non disponible",
    "address": "\n49 bis Mouaouia ibn Abi Sofiane, Ariana 2091",
    "phone": "\n58 959 000",
    "website": "https://support.google.com/contributionpolicy/answer/7400114?ref_topic=7422769"
  },
  {
    "title": "Dar El Osra Charlemagne café",
    "rating": "Non disponible",
    "reviews": "Non disponible",
    "address": "\nV526+4P5, Rue du Lycée, Ariana",
    "phone": "Non disponible",
    "website": "https://business.google.com/create?fp=14888368640407107741&hl=ar&authuser=0&gmbsrc=tn-ar-et-ip-z-gmb-s-z-l~mrc%7Cclaimbz%7Cu&ppsrc=GMBMI&utm_campaign=tn-ar-et-ip-z-gmb-s-z-l~mrc%7Cclaimbz%7Cu&utm_source=gmb_mrc81&utm_medium=et&getstarted&lis=0"
  },
  {
    "title": "Symbiose Healthy Tasty Food",
    "rating": "Non disponible",
    "reviews": "Non disponible",
    "address": "\n2 Rue Halima Essaadia, Tunis 2091",
    "phone": "\n56 561 210",
    "website": "https://www.google.com/maps/contrib/117977912193118530779"
  },
  {
    "title": "Sunshine coffee shop",
    "rating": "Non disponible",
    "reviews": "Non disponible",
    "address": "\nR5V8+HGG, Othmane Ibn Affane, Av. Othman Ibn Affane, Ariana",
    "phone": "\n50 749 765",
    "website": "https://business.google.com/create?fp=10819357181002588921&hl=ar&authuser=0&gmbsrc=tn-ar-et-ip-z-gmb-s-z-l~mrc%7Cclaimbz%7Cu&ppsrc=GMBMI&utm_campaign=tn-ar-et-ip-z-gmb-s-z-l~mrc%7Cclaimbz%7Cu&utm_source=gmb_mrc81&utm_medium=et&getstarted&lis=0"
  },
  {
    "title": "New Luxemboug café/lounge",
    "rating": "Non disponible",
    "reviews": "Non disponible",
    "address": "\nعزيزة عثمانة، 7 Rue 2091, Ariana",
    "phone": "\n93 681 829",
    "website": "https://business.google.com/create?fp=7868853919069113508&hl=ar&authuser=0&gmbsrc=tn-ar-et-ip-z-gmb-s-z-l~mrc%7Cclaimbz%7Cu&ppsrc=GMBMI&utm_campaign=tn-ar-et-ip-z-gmb-s-z-l~mrc%7Cclaimbz%7Cu&utm_source=gmb_mrc81&utm_medium=et&getstarted&lis=0"
  },
  {
    "title": "RedFrog Coffee",
    "rating": "Non disponible",
    "reviews": "Non disponible",
    "address": "\n50 Ter 1004, Ave d'Afrique, Ariana",
    "phone": "Non disponible",
    "website": "https://www.facebook.com/ReDFROG2/"
  },
  {
    "title": "THE BOTTLE coffee",
    "rating": "Non disponible",
    "reviews": "Non disponible",
    "address": "\nV53F+QRV، أريانة",
    "phone": "\n70 741 531",
    "website": "https://business.google.com/create?fp=8421877096201117018&hl=ar&authuser=0&gmbsrc=tn-ar-et-ip-z-gmb-s-z-l~mrc%7Cclaimbz%7Cu&ppsrc=GMBMI&utm_campaign=tn-ar-et-ip-z-gmb-s-z-l~mrc%7Cclaimbz%7Cu&utm_source=gmb_mrc81&utm_medium=et&getstarted&lis=0"
  },
  {
    "title": "Zazoua Café",
    "rating": "Non disponible",
    "reviews": "Non disponible",
    "address": "\nRue Mouawiya Ibn Abi Sofiene، أريانة",
    "phone": "\n92 445 040",
    "website": "http://zazoua.intouch.org.tn/"
  },
  {
    "title": "Café 33",
    "rating": "Non disponible",
    "reviews": "Non disponible",
    "address": "\nR5VC+M23, Rue Ahmed Tlili, Ariana",
    "phone": "\n21 837 025",
    "website": "https://business.google.com/create?fp=10590468578786104255&hl=ar&authuser=0&gmbsrc=tn-ar-et-ip-z-gmb-s-z-l~mrc%7Cclaimbz%7Cu&ppsrc=GMBMI&utm_campaign=tn-ar-et-ip-z-gmb-s-z-l~mrc%7Cclaimbz%7Cu&utm_source=gmb_mrc81&utm_medium=et&getstarted&lis=0"
  },
  {
    "title": "Crepes Factory",
    "rating": "Non disponible",
    "reviews": "Non disponible",
    "address": "\n15 bis, 5 Rue Mouawiya Ibn Abi Sofien, Ariana 2080",
    "phone": "\n99 960 994",
    "website": "https://glovoapp.com/tn/fr/tunis-1-tunis-centre-menzah-manar/crepe-factory-tis?utm_source=google&utm_medium=organic&utm_campaign=google_reserve_place_order_action"
  },
  {
    "title": "Zaz Bistro Zinzin",
    "rating": "Non disponible",
    "reviews": "Non disponible",
    "address": "\n95 Avenue Mouaouia Ibn Abi Sofiane, Ariana",
    "phone": "\n92 445 040",
    "website": "https://www.facebook.com/Zazbistrozinzin/posts/pfbid02Z7D9MAoUnKjN34rHiboDDVyzZybmSEeAMBevftTif7H2dbf49P3RJ7zbSckFVXoLl"
  },
  {
    "title": "Safood eat&drink",
    "rating": "Non disponible",
    "reviews": "Non disponible",
    "address": "\nibn yassir, 12 Rue Ammar Ibn Yasser، Ariana",
    "phone": "\n55 116 117",
    "website": "https://support.google.com/contributionpolicy/answer/7400114?ref_topic=7422769"
  },
  {
    "title": "Everest Coffee",
    "rating": "Non disponible",
    "reviews": "Non disponible",
    "address": "\n2 Ter dhiaf, Rue Ibn Abi Dhiaf, Ariana 2091",
    "phone": "Non disponible",
    "website": "https://support.google.com/contributionpolicy/answer/7400114?ref_topic=7422769"
  },
  {
    "title": "YoYo food",
    "rating": "Non disponible",
    "reviews": "Non disponible",
    "address": "\n18 Rue des juges, Ariana 2091",
    "phone": "Non disponible",
    "website": "https://business.google.com/create?fp=2593517857277786396&hl=ar&authuser=0&gmbsrc=tn-ar-et-ip-z-gmb-s-z-l~mrc%7Cclaimbz%7Cu&ppsrc=GMBMI&utm_campaign=tn-ar-et-ip-z-gmb-s-z-l~mrc%7Cclaimbz%7Cu&utm_source=gmb_mrc81&utm_medium=et&getstarted&lis=0"
  },
  {
    "title": "Restaurant Route66 Menzah6",
    "rating": "Non disponible",
    "reviews": "Non disponible",
    "address": "\n17 Rue Ammar Ibn Yesser, Ariana 2091",
    "phone": "\n71 234 448",
    "website": "https://glovoapp.com/tn/fr/tunis-1-tunis-centre-menzah-manar/route-66-menzah-6-tis?utm_source=google&utm_medium=organic&utm_campaign=google_reserve_place_order_action"
  },
  {
    "title": "Cafeino",
    "rating": "Non disponible",
    "reviews": "Non disponible",
    "address": "\n17 Rue Abou Loubéba Al Ansari, Ariana",
    "phone": "Non disponible",
    "website": "https://support.google.com/contributionpolicy/answer/7400114?ref_topic=7422769"
  },
  {
    "title": "Manzah yoyo",
    "rating": "Non disponible",
    "reviews": "Non disponible",
    "address": "\nR5W7+3VX، أريانة",
    "phone": "Non disponible",
    "website": "https://business.google.com/create?fp=535958778855178603&hl=ar&authuser=0&gmbsrc=tn-ar-et-ip-z-gmb-s-z-l~mrc%7Cclaimbz%7Cu&ppsrc=GMBMI&utm_campaign=tn-ar-et-ip-z-gmb-s-z-l~mrc%7Cclaimbz%7Cu&utm_source=gmb_mrc81&utm_medium=et&getstarted&lis=0"
  },
  {
    "title": "Pizza Tiburtina",
    "rating": "Non disponible",
    "reviews": "Non disponible",
    "address": "\nR5W8+P8V، أريانة",
    "phone": "\n21 178 684",
    "website": "https://m.facebook.com/TiburtinaMenzah6/"
  },
  {
    "title": "Ashk Sweet and Salty Tunisia",
    "rating": "Non disponible",
    "reviews": "Non disponible",
    "address": "\n83 Ave d'Afrique, Ariana",
    "phone": "\n24 666 466",
    "website": "https://business.google.com/create?fp=5778794573949423459&hl=ar&authuser=0&gmbsrc=tn-ar-et-ip-z-gmb-s-z-l~mrc%7Cclaimbz%7Cu&ppsrc=GMBMI&utm_campaign=tn-ar-et-ip-z-gmb-s-z-l~mrc%7Cclaimbz%7Cu&utm_source=gmb_mrc81&utm_medium=et&getstarted&lis=0"
  },
  {
    "title": "Z coffee",
    "rating": "Non disponible",
    "reviews": "Non disponible",
    "address": "\nV53C+487، أريانة",
    "phone": "Non disponible",
    "website": "https://business.google.com/create?fp=2236280313451217814&hl=ar&authuser=0&gmbsrc=tn-ar-et-ip-z-gmb-s-z-l~mrc%7Cclaimbz%7Cu&ppsrc=GMBMI&utm_campaign=tn-ar-et-ip-z-gmb-s-z-l~mrc%7Cclaimbz%7Cu&utm_source=gmb_mrc81&utm_medium=et&getstarted&lis=0"
  },
  {
    "title": "The Sunny Beans 더써니빈",
    "rating": "Non disponible",
    "reviews": "Non disponible",
    "address": "\nUV4 N°66 cité wifek، el menzah 6، Ariana, 2091",
    "phone": "\n50 398 080",
    "website": "https://www.facebook.com/TheSunnyBeans/"
  },
  {
    "title": "Casa De Papel Menzah 9",
    "rating": "Non disponible",
    "reviews": "Non disponible",
    "address": "\nتونس",
    "phone": "\n71 875 032",
    "website": "https://m.facebook.com/pages/category/Cafe/La-Casa-De-Papel-Lounge-100991435257002/"
  },
  {
    "title": "The Moon Menzah7",
    "rating": "Non disponible",
    "reviews": "Non disponible",
    "address": "\n114 Rue Mouawiya Ibn Abi Sofiene، أريانة 2037",
    "phone": "\n20 202 266",
    "website": "https://www.facebook.com/profile.php?id=61559196106695&mibextid=LQQJ4d"
  },
  {
    "title": "Damascino",
    "rating": "Non disponible",
    "reviews": "Non disponible",
    "address": "\n38 Rue Mouawiya Ibn Abi Sofiene, Ariana",
    "phone": "\n51 514 080",
    "website": "https://glovoapp.com/tn/fr/tunis-1-tunis-centre-menzah-manar/damascino-tis?utm_source=google&utm_medium=organic&utm_campaign=google_reserve_place_order_action"
  },
  {
    "title": "Barista's Menzah 1",
    "rating": "Non disponible",
    "reviews": "Non disponible",
    "address": "\n01 نهج جبل الرصاص، تونس",
    "phone": "\n70 030 824",
    "website": "https://m.facebook.com/Baristas-Menzah-1500692783333011/?ref=page_internal&mt_nav=0&locale2=fr_FR"
  },
  {
    "title": "Café El Amir",
    "rating": "Non disponible",
    "reviews": "Non disponible",
    "address": "\nV535+3QV، أريانة",
    "phone": "Non disponible",
    "website": "https://business.google.com/create?fp=13166679099591255096&hl=ar&authuser=0&gmbsrc=tn-ar-et-ip-z-gmb-s-z-l~mrc%7Cclaimbz%7Cu&ppsrc=GMBMI&utm_campaign=tn-ar-et-ip-z-gmb-s-z-l~mrc%7Cclaimbz%7Cu&utm_source=gmb_mrc81&utm_medium=et&getstarted&lis=0"
  },
  {
    "title": "Red light",
    "rating": "Non disponible",
    "reviews": "Non disponible",
    "address": "\n5D, El Menzah 7 (47, 5C, Ariana",
    "phone": "Non disponible",
    "website": "https://support.google.com/contributionpolicy/answer/7400114?ref_topic=7422769"
  },
  {
    "title": "Trocadero",
    "rating": "Non disponible",
    "reviews": "Non disponible",
    "address": "\nR5VC+PC2، أريانة",
    "phone": "\n25 404 536",
    "website": "https://business.google.com/create?fp=5762155066399131041&hl=ar&authuser=0&gmbsrc=tn-ar-et-ip-z-gmb-s-z-l~mrc%7Cclaimbz%7Cu&ppsrc=GMBMI&utm_campaign=tn-ar-et-ip-z-gmb-s-z-l~mrc%7Cclaimbz%7Cu&utm_source=gmb_mrc81&utm_medium=et&getstarted&lis=0"
  },
  {
    "title": "Echemi Menzah 5",
    "rating": "Non disponible",
    "reviews": "Non disponible",
    "address": "\nAvenue Ahmed Tlili، أريانة",
    "phone": "Non disponible",
    "website": "https://business.google.com/create?fp=14953669851697052172&hl=ar&authuser=0&gmbsrc=tn-ar-et-ip-z-gmb-s-z-l~mrc%7Cclaimbz%7Cu&ppsrc=GMBMI&utm_campaign=tn-ar-et-ip-z-gmb-s-z-l~mrc%7Cclaimbz%7Cu&utm_source=gmb_mrc81&utm_medium=et&getstarted&lis=0"
  },
  {
    "title": "Le Comptoir des Délices",
    "rating": "Non disponible",
    "reviews": "Non disponible",
    "address": "\nV537+3X6, manezah centre, أريانة",
    "phone": "\n26 599 652",
    "website": "https://business.google.com/create?fp=10509539039037727196&hl=ar&authuser=0&gmbsrc=tn-ar-et-ip-z-gmb-s-z-l~mrc%7Cclaimbz%7Cu&ppsrc=GMBMI&utm_campaign=tn-ar-et-ip-z-gmb-s-z-l~mrc%7Cclaimbz%7Cu&utm_source=gmb_mrc81&utm_medium=et&getstarted&lis=0"
  },
  {
    "title": "JamJem",
    "rating": "Non disponible",
    "reviews": "Non disponible",
    "address": "\n15 Rue Abou Loubéba Al Ansari, Ariana",
    "phone": "\n58 030 031",
    "website": "https://glovoapp.com/tn/fr/tunis-1-tunis-centre-menzah-manar/chapati-mahdia?utm_source=google&utm_medium=organic&utm_campaign=google_reserve_place_order_action"
  },
  {
    "title": "La Brisa Café & Restaurant",
    "rating": "Non disponible",
    "reviews": "Non disponible",
    "address": "\nأريانة 2092",
    "phone": "\n23 364 800",
    "website": "https://support.google.com/contributionpolicy/answer/7400114?ref_topic=7422769"
  },
  {
    "title": "Fifty Shades Coffee Menzah 5",
    "rating": "Non disponible",
    "reviews": "Non disponible",
    "address": "\nV52H+732, Av. de la liberté, Ariana",
    "phone": "\n20 048 027",
    "website": "https://business.google.com/create?fp=8492114168738443760&hl=ar&authuser=0&gmbsrc=tn-ar-et-ip-z-gmb-s-z-l~mrc%7Cclaimbz%7Cu&ppsrc=GMBMI&utm_campaign=tn-ar-et-ip-z-gmb-s-z-l~mrc%7Cclaimbz%7Cu&utm_source=gmb_mrc81&utm_medium=et&getstarted&lis=0"
  },
  {
    "title": "Le Chat Noir, Espresso bar",
    "rating": "Non disponible",
    "reviews": "Non disponible",
    "address": "\n8 Ter, Av. Salah Ben Youssef، تونس 1013",
    "phone": "\n55 621 770",
    "website": "https://support.google.com/contributionpolicy/answer/7400114?ref_topic=7422769"
  },
  {
    "title": "Yoyo food",
    "rating": "Non disponible",
    "reviews": "Non disponible",
    "address": "\n61 Ave d'Afrique, Ariana",
    "phone": "\n98 541 229",
    "website": "https://www.facebook.com/yoyochocoland"
  },
  {
    "title": "مطعم واتس اب",
    "rating": "Non disponible",
    "reviews": "Non disponible",
    "address": "\nV52H+73C, Av. de la liberté, Ariana",
    "phone": "\n52 669 566",
    "website": "https://m.facebook.com/whatsuptunis/"
  },
  {
    "title": "Bistrot Coffee DS",
    "rating": "Non disponible",
    "reviews": "Non disponible",
    "address": "\n90b Avenue Ibn Abi Sofiene, Ariana",
    "phone": "Non disponible",
    "website": "https://business.google.com/create?fp=15643724313841913526&hl=ar&authuser=0&gmbsrc=tn-ar-et-ip-z-gmb-s-z-l~mrc%7Cclaimbz%7Cu&ppsrc=GMBMI&utm_campaign=tn-ar-et-ip-z-gmb-s-z-l~mrc%7Cclaimbz%7Cu&utm_source=gmb_mrc81&utm_medium=et&getstarted&lis=0"
  },
  {
    "title": "HATTAB",
    "rating": "Non disponible",
    "reviews": "Non disponible",
    "address": "\nR5W8+XGX, Rue Cheikh Zaghouani, Ariana",
    "phone": "\n93 084 393",
    "website": "https://business.google.com/create?fp=10224671260365972217&hl=ar&authuser=0&gmbsrc=tn-ar-et-ip-z-gmb-s-z-l~mrc%7Cclaimbz%7Cu&ppsrc=GMBMI&utm_campaign=tn-ar-et-ip-z-gmb-s-z-l~mrc%7Cclaimbz%7Cu&utm_source=gmb_mrc81&utm_medium=et&getstarted&lis=0"
  },
  {
    "title": "ال في كلب كافييه",
    "rating": "Non disponible",
    "reviews": "Non disponible",
    "address": "\n18 Av. de la liberté, Ariana",
    "phone": "\n22 835 284",
    "website": "https://business.google.com/create?fp=9263651035443395244&hl=ar&authuser=0&gmbsrc=tn-ar-et-ip-z-gmb-s-z-l~mrc%7Cclaimbz%7Cu&ppsrc=GMBMI&utm_campaign=tn-ar-et-ip-z-gmb-s-z-l~mrc%7Cclaimbz%7Cu&utm_source=gmb_mrc81&utm_medium=et&getstarted&lis=0"
  },
  {
    "title": "La Terrasse Carnoy",
    "rating": "Non disponible",
    "reviews": "Non disponible",
    "address": "\n36 Rue Ahmed Tlili, Ariana",
    "phone": "\n71 766 336",
    "website": "https://support.google.com/contributionpolicy/answer/7400114?ref_topic=7422769"
  },
  {
    "title": "Pizza djeeck",
    "rating": "Non disponible",
    "reviews": "Non disponible",
    "address": "\n17 Rue Abouloubaba Al Ansari, Ariana",
    "phone": "\n71 238 323",
    "website": "https://support.google.com/contributionpolicy/answer/7400114?ref_topic=7422769"
  },
  {
    "title": "Cosmitto",
    "rating": "Non disponible",
    "reviews": "Non disponible",
    "address": "\nR5WM+296, Tunis",
    "phone": "\n24 855 341",
    "website": "https://glovoapp.com/tn/fr/tunis-1-tunis-centre-menzah-manar/cosmitto-centre-ville-tis?utm_source=google&utm_medium=organic&utm_campaign=google_reserve_place_order_action"
  },
  {
    "title": "Ô Four !",
    "rating": "Non disponible",
    "reviews": "Non disponible",
    "address": "\n64 Rue Mouawiya Ibn Abi Sofiene, Ariana",
    "phone": "\n52 123 355",
    "website": "https://glovoapp.com/tn/fr/tunis-1-tunis-centre-menzah-manar/o-four-tis?utm_source=google&utm_medium=organic&utm_campaign=google_reserve_place_order_action"
  },
  {
    "title": "FunHouse",
    "rating": "Non disponible",
    "reviews": "Non disponible",
    "address": "\n25 Rue Mohamed El Hlioui، أريانة",
    "phone": "Non disponible",
    "website": "https://business.google.com/create?fp=175873591499011261&hl=ar&authuser=0&gmbsrc=tn-ar-et-ip-z-gmb-s-z-l~mrc%7Cclaimbz%7Cu&ppsrc=GMBMI&utm_campaign=tn-ar-et-ip-z-gmb-s-z-l~mrc%7Cclaimbz%7Cu&utm_source=gmb_mrc81&utm_medium=et&getstarted&lis=0"
  },
  {
    "title": "Fricasso",
    "rating": "Non disponible",
    "reviews": "Non disponible",
    "address": "\nCite jamil M6 boutique n2 Ariana, 2692",
    "phone": "\n28 329 328",
    "website": "https://glovoapp.com/tn/fr/tunis-1-tunis-centre-menzah-manar/fricasso-tis?utm_source=google&utm_medium=organic&utm_campaign=google_reserve_place_order_action"
  },
  {
    "title": "Gourmandise menzah 5",
    "rating": "Non disponible",
    "reviews": "Non disponible",
    "address": "\n38 Rue Mouawiya Ibn Abi Sofiene, Ariana",
    "phone": "\n29 740 252",
    "website": "https://glovoapp.com/tn/fr/tunis-1-tunis-centre-menzah-manar/goumandise-menzah-5?utm_source=google&utm_medium=organic&utm_campaign=google_reserve_place_order_action"
  },
  {
    "title": "Eric Kayser",
    "rating": "Non disponible",
    "reviews": "Non disponible",
    "address": "\nV53F+G2G, Rue Mustapha Abdessalem, Ariana",
    "phone": "Non disponible",
    "website": "https://glovoapp.com/tn/fr/tunis-1-tunis-centre-menzah-manar/maison-eric-kayser-menzah-5-tis?utm_source=google&utm_medium=organic&utm_campaign=google_reserve_place_order_action"
  },
  {
    "title": "Emperor Gaming Club",
    "rating": "Non disponible",
    "reviews": "Non disponible",
    "address": "\n2ème étage, 17, 6 Rue Abou Loubéba Al Ansari, Ariana 2091",
    "phone": "\n99 544 409",
    "website": "https://www.google.com/maps/contrib/107348776444639278218"
  },
  {
    "title": "Mme Rekik La Pâtissière",
    "rating": "Non disponible",
    "reviews": "Non disponible",
    "address": "\n48 Rue Ahmed Tlili, Ariana",
    "phone": "\n28 444 000",
    "website": "http://www.patisserie-rekik.com/"
  },
  {
    "title": "Malmö Coffee Tunis",
    "rating": "Non disponible",
    "reviews": "Non disponible",
    "address": "\nR5W4+47R, Unnamed Road, Tunis",
    "phone": "\n20 105 334",
    "website": "https://business.google.com/create?fp=11672430450136565033&hl=ar&authuser=0&gmbsrc=tn-ar-et-ip-z-gmb-s-z-l~mrc%7Cclaimbz%7Cu&ppsrc=GMBMI&utm_campaign=tn-ar-et-ip-z-gmb-s-z-l~mrc%7Cclaimbz%7Cu&utm_source=gmb_mrc81&utm_medium=et&getstarted&lis=0"
  },
  {
    "title": "Crêpe Factory Menzah 8",
    "rating": "Non disponible",
    "reviews": "Non disponible",
    "address": "\nV53C+G29, Av. Othman Ibn Affane, Ariana",
    "phone": "\n55 558 494",
    "website": "https://business.google.com/create?fp=18162316748417615243&hl=ar&authuser=0&gmbsrc=tn-ar-et-ip-z-gmb-s-z-l~mrc%7Cclaimbz%7Cu&ppsrc=GMBMI&utm_campaign=tn-ar-et-ip-z-gmb-s-z-l~mrc%7Cclaimbz%7Cu&utm_source=gmb_mrc81&utm_medium=et&getstarted&lis=0"
  },
  {
    "title": "cars & coffee",
    "rating": "Non disponible",
    "reviews": "Non disponible",
    "address": "\nR5V8+QF9, Av. Othman Ibn Affane, Tunis",
    "phone": "\n55 786 644",
    "website": "https://business.google.com/create?fp=3929284634252095887&hl=ar&authuser=0&gmbsrc=tn-ar-et-ip-z-gmb-s-z-l~mrc%7Cclaimbz%7Cu&ppsrc=GMBMI&utm_campaign=tn-ar-et-ip-z-gmb-s-z-l~mrc%7Cclaimbz%7Cu&utm_source=gmb_mrc81&utm_medium=et&getstarted&lis=0"
  },
  {
    "title": "Café Chams",
    "rating": "Non disponible",
    "reviews": "Non disponible",
    "address": "\n27 Av. mongi slim, Ariana",
    "phone": "\n23 287 883",
    "website": "https://business.google.com/create?fp=12487821379641848497&hl=ar&authuser=0&gmbsrc=tn-ar-et-ip-z-gmb-s-z-l~mrc%7Cclaimbz%7Cu&ppsrc=GMBMI&utm_campaign=tn-ar-et-ip-z-gmb-s-z-l~mrc%7Cclaimbz%7Cu&utm_source=gmb_mrc81&utm_medium=et&getstarted&lis=0"
  },
  {
    "title": "Patisserie Sfaxiene",
    "rating": "Non disponible",
    "reviews": "Non disponible",
    "address": "\nR5X7+VVX, Rue Ammar Ibn Yesser, Ariana",
    "phone": "Non disponible",
    "website": "https://business.google.com/create?fp=7837365572453486351&hl=ar&authuser=0&gmbsrc=tn-ar-et-ip-z-gmb-s-z-l~mrc%7Cclaimbz%7Cu&ppsrc=GMBMI&utm_campaign=tn-ar-et-ip-z-gmb-s-z-l~mrc%7Cclaimbz%7Cu&utm_source=gmb_mrc81&utm_medium=et&getstarted&lis=0"
  },
  {
    "title": "Le Monde Est Petit",
    "rating": "Non disponible",
    "reviews": "Non disponible",
    "address": "\nibn yasser،, 26 rue ammar ibn yasser, Ariana",
    "phone": "\n21 080 631",
    "website": "https://business.google.com/create?fp=17414522738473277069&hl=ar&authuser=0&gmbsrc=tn-ar-et-ip-z-gmb-s-z-l~mrc%7Cclaimbz%7Cu&ppsrc=GMBMI&utm_campaign=tn-ar-et-ip-z-gmb-s-z-l~mrc%7Cclaimbz%7Cu&utm_source=gmb_mrc81&utm_medium=et&getstarted&lis=0"
  }
]